ichi_auth/__init__.py
ichi_auth/auth_config.py
ichi_auth/auth_jwt.py
ichi_auth/config.py
ichi_auth/exceptions.py
ichi_auth-1.1.dist-info/LICENSE
ichi_auth-1.1.dist-info/WHEEL
ichi_auth-1.1.dist-info/METADATA
ichi_auth-1.1.dist-info/RECORD
