Metadata-Version: 2.1
Name: ichi-auth
Version: 1.1
Summary: FastAPI extension that provides JWT Auth support (secure, easy to use and lightweight)
Author-email: Nyoman Pradipta Dewantara <nyomanpradipta120@gmail.com>, aveeryy <aveeryy@protonmail.com>
Requires-Python: >=3.7
Classifier: Environment :: Web Environment
Classifier: Intended Audience :: Developers
Classifier: Programming Language :: Python :: 3
Classifier: Programming Language :: Python :: 3.7
Classifier: Programming Language :: Python :: 3.8
Classifier: Programming Language :: Python :: 3.9
Classifier: Programming Language :: Python :: 3.10
Classifier: License :: OSI Approved :: MIT License
Classifier: Operating System :: OS Independent
Classifier: Topic :: Internet :: WWW/HTTP :: Dynamic Content
Classifier: Topic :: Software Development :: Libraries :: Python Modules
Requires-Dist: fastapi>=0.65.2
Requires-Dist: PyJWT>=2.6.0
Requires-Dist: cryptography>=38.0.3 ; extra == "asymmetric"
Requires-Dist: cryptography>=38.0.3 ; extra == "dev"
Requires-Dist: uvicorn>=0.19.0 ; extra == "dev"
Requires-Dist: mkdocs>=1.1.2,<2.0.0 ; extra == "doc"
Requires-Dist: mkdocs-material>=5.5.0,<6.0.0 ; extra == "doc"
Requires-Dist: markdown-include>=0.5.1,<0.6.0 ; extra == "doc"
Requires-Dist: pytest==6.2.5 ; extra == "test"
Requires-Dist: pytest-cov==4.0.0 ; extra == "test"
Requires-Dist: coveralls==3.3.1 ; extra == "test"
Requires-Dist: httpx==0.23.0 ; extra == "test"
Project-URL: Home, https://codeberg.org/ichi/auth
Provides-Extra: asymmetric
Provides-Extra: dev
Provides-Extra: doc
Provides-Extra: test
